ffmpeg_ai/__init__.py
ffmpeg_ai/cache.py
ffmpeg_ai/cli.py
ffmpeg_ai/llm_engine.py
ffmpeg_ai/retriever.py
ffmpeg_ai/setup.py
ffmpeg_ai/utils.py
ffmpeg_ai-0.1.8.dist-info/METADATA
ffmpeg_ai-0.1.8.dist-info/WHEEL
ffmpeg_ai-0.1.8.dist-info/entry_points.txt
ffmpeg_ai-0.1.8.dist-info/top_level.txt
ffmpeg_ai-0.1.8.dist-info/RECORD
