Metadata-Version: 2.4
Name: ffmpeg-ai
Version: 0.1.8
Summary: AI-powered FFmpeg command generator
Home-page: https://github.com/Aliasgar-Jiwani/ffmpeg-ai
Author: Aliasgar Jiwani
Author-email: aliasgarjiwani@gmail.com
Classifier: Programming Language :: Python :: 3
Classifier: License :: OSI Approved :: MIT License
Classifier: Operating System :: OS Independent
Requires-Python: >=3.8
Requires-Dist: typer
Requires-Dist: rich
Requires-Dist: langchain
Requires-Dist: ollama
Requires-Dist: chromadb
Requires-Dist: requests
Requires-Dist: beautifulsoup4
Requires-Dist: html2text
Requires-Dist: langchain-huggingface
Dynamic: author
Dynamic: author-email
Dynamic: classifier
Dynamic: description
Dynamic: description-content-type
Dynamic: home-page
Dynamic: requires-dist
Dynamic: requires-python
Dynamic: summary
